jhat/__init__.py
jhat/pdastro.py
jhat/simple_jwst_phot.py
jhat/simple_jwst_phot_temp.py
jhat/st_wcs_align.py
jhat/st_wcs_align_batch.py
jhat/st_wcs_align_temp.py
jhat/test_jhat.py
jhat-0.3.5.dist-info/METADATA
jhat-0.3.5.dist-info/WHEEL
jhat-0.3.5.dist-info/top_level.txt
jhat-0.3.5.dist-info/RECORD
