Metadata-Version: 2.4
Name: jhat
Version: 0.3.5
Author-email: Armin Rest & Justin Pierel <arest@stsci.edu>
Project-URL: Homepage, https://jhat.readthedocs.io/en/latest/
Requires-Python: >=3.0
Requires-Dist: argparse
Requires-Dist: numpy
Requires-Dist: matplotlib
Requires-Dist: astropy
Requires-Dist: jwst>=1.17
Requires-Dist: scipy
Requires-Dist: photutils
Requires-Dist: pysiaf
Requires-Dist: astroquery
Requires-Dist: pandas>=1.5
Requires-Dist: stsci.skypac
Requires-Dist: tweakreg_hack
Requires-Dist: tweakwcs>=0.8
Requires-Dist: pytest-astropy
